polyinterface/__init__.py
polyinterface/polyinterface.py
polyinterface/polylogger.py
polyinterface-2.1.0.dist-info/LICENSE
polyinterface-2.1.0.dist-info/METADATA
polyinterface-2.1.0.dist-info/WHEEL
polyinterface-2.1.0.dist-info/top_level.txt
polyinterface-2.1.0.dist-info/RECORD
