Metadata-Version: 2.1
Name: polyinterface
Version: 2.1.0
Summary: UDI Polyglot v2 Interface
Home-page: https://github.com/UniversalDevicesInc/polyglot-v2-python-interface
Author: James Milne
Author-email: milne.james@gmail.com
License: MIT
Platform: UNKNOWN
Classifier: Development Status :: 5 - Production/Stable
Classifier: License :: OSI Approved :: MIT License
Classifier: Programming Language :: Python :: 2.7
Classifier: Programming Language :: Python :: 3.3
Classifier: Programming Language :: Python :: 3.4
Classifier: Programming Language :: Python :: 3.5
Classifier: Programming Language :: Python :: 3.6
Requires-Python: >2.7,!=3.0.*,!=3.1.*,!=3.2.*
Requires-Dist: paho-mqtt
Requires-Dist: python-dotenv
Requires-Dist: markdown2
Requires-Dist: netifaces
